[
    {
        "kurzbezeichnung": "Prof.-Gerstmayr-Straße",
        "id": 60435,
        "strassenbezeichnung": "Prof.-Gerstmayr-Straße"
    },
    {
        "kurzbezeichnung": "Prof.-Gerstmayr-Weg",
        "id": 60436,
        "strassenbezeichnung": "Prof.-Gerstmayr-Weg"
    },
    {
        "kurzbezeichnung": "Hinterholz",
        "id": 84340,
        "strassenbezeichnung": "Hinterholz"
    },
    {
        "kurzbezeichnung": "Machlandstraße",
        "id": 93110,
        "strassenbezeichnung": "Machlandstraße"
    },
    {
        "kurzbezeichnung": "Perger Straße",
        "id": 93111,
        "strassenbezeichnung": "Perger Straße"
    }
]