[
    {
        "kurzbezeichnung": "Kastanienweg",
        "id": 101691,
        "strassenbezeichnung": "Kastanienweg"
    },
    {
        "kurzbezeichnung": "Kirchenweg",
        "id": 101688,
        "strassenbezeichnung": "Kirchenweg"
    },
    {
        "kurzbezeichnung": "Kirschenweg",
        "id": 101686,
        "strassenbezeichnung": "Kirschenweg"
    },
    {
        "kurzbezeichnung": "Oleanderweg",
        "id": 101690,
        "strassenbezeichnung": "Oleanderweg"
    },
    {
        "kurzbezeichnung": "Pürkerweg",
        "id": 101679,
        "strassenbezeichnung": "Pürkerweg"
    },
    {
        "kurzbezeichnung": "Schloßstraße",
        "id": 101683,
        "strassenbezeichnung": "Schloßstraße"
    },
    {
        "kurzbezeichnung": "Schrimitzerstraße",
        "id": 101682,
        "strassenbezeichnung": "Schrimitzerstraße"
    },
    {
        "kurzbezeichnung": "Seerosenweg",
        "id": 101685,
        "strassenbezeichnung": "Seerosenweg"
    },
    {
        "kurzbezeichnung": "Tannenweg",
        "id": 101687,
        "strassenbezeichnung": "Tannenweg"
    },
    {
        "kurzbezeichnung": "Veilchenweg",
        "id": 101684,
        "strassenbezeichnung": "Veilchenweg"
    },
    {
        "kurzbezeichnung": "Wielenweg",
        "id": 101689,
        "strassenbezeichnung": "Wielenweg"
    },
    {
        "kurzbezeichnung": "Witscher Weg",
        "id": 101681,
        "strassenbezeichnung": "Witscher Weg"
    },
    {
        "kurzbezeichnung": "Tigringer Straße",
        "id": 6208,
        "strassenbezeichnung": "Tigringer Straße"
    },
    {
        "kurzbezeichnung": "Lindenweg",
        "id": 101669,
        "strassenbezeichnung": "Lindenweg"
    }
]