[
    {
        "kurzbezeichnung": "Aignerstraße",
        "id": 115110,
        "strassenbezeichnung": "Aignerstraße"
    },
    {
        "kurzbezeichnung": "Alois-Ulm-Weg",
        "id": 92710,
        "strassenbezeichnung": "Alois-Ulm-Weg"
    },
    {
        "kurzbezeichnung": "Amselweg",
        "id": 52338,
        "strassenbezeichnung": "Amselweg"
    },
    {
        "kurzbezeichnung": "Anton-Bruckner-Straße",
        "id": 115109,
        "strassenbezeichnung": "Anton-Bruckner-Straße"
    },
    {
        "kurzbezeichnung": "Anton-Payr-Straße",
        "id": 30054,
        "strassenbezeichnung": "Anton-Payr-Straße"
    },
    {
        "kurzbezeichnung": "Atterseestraße",
        "id": 30055,
        "strassenbezeichnung": "Atterseestraße"
    },
    {
        "kurzbezeichnung": "Aussichtsweg",
        "id": 30056,
        "strassenbezeichnung": "Aussichtsweg"
    },
    {
        "kurzbezeichnung": "Bahnweg",
        "id": 30057,
        "strassenbezeichnung": "Bahnweg"
    },
    {
        "kurzbezeichnung": "Beim Amthof",
        "id": 92711,
        "strassenbezeichnung": "Beim Amthof"
    },
    {
        "kurzbezeichnung": "Bergstraße",
        "id": 67299,
        "strassenbezeichnung": "Bergstraße"
    },
    {
        "kurzbezeichnung": "Bocksleitnerweg",
        "id": 30058,
        "strassenbezeichnung": "Bocksleitnerweg"
    },
    {
        "kurzbezeichnung": "Carl-Häupl-Weg",
        "id": 30059,
        "strassenbezeichnung": "Carl-Häupl-Weg"
    },
    {
        "kurzbezeichnung": "Carl-Leiß-Straße",
        "id": 92714,
        "strassenbezeichnung": "Carl-Leiß-Straße"
    },
    {
        "kurzbezeichnung": "Dorothea-Jörger-Straße",
        "id": 67302,
        "strassenbezeichnung": "Dorothea-Jörger-Straße"
    },
    {
        "kurzbezeichnung": "Dr.-F.-C.-Ginzkey-Weg",
        "id": 30062,
        "strassenbezeichnung": "Dr.-Franz-Carl-Ginzkey-Weg"
    },
    {
        "kurzbezeichnung": "Dr.-Fritz-Seifert-Str.",
        "id": 30060,
        "strassenbezeichnung": "Dr.-Fritz-Seifert-Straße"
    },
    {
        "kurzbezeichnung": "Dr.-Rudolf-Schuh-Str.",
        "id": 30061,
        "strassenbezeichnung": "Dr.-Rudolf-Schuh-Straße"
    },
    {
        "kurzbezeichnung": "Feldstraße",
        "id": 30063,
        "strassenbezeichnung": "Feldstraße"
    },
    {
        "kurzbezeichnung": "Flößerweg",
        "id": 30064,
        "strassenbezeichnung": "Flößerweg"
    },
    {
        "kurzbezeichnung": "Freyungerstraße",
        "id": 96174,
        "strassenbezeichnung": "Freyungerstraße"
    },
    {
        "kurzbezeichnung": "Haidacher Straße",
        "id": 30065,
        "strassenbezeichnung": "Haidacher Straße"
    },
    {
        "kurzbezeichnung": "Haininger Bach",
        "id": 30066,
        "strassenbezeichnung": "Haininger Bach"
    },
    {
        "kurzbezeichnung": "Hatschekstraße",
        "id": 30067,
        "strassenbezeichnung": "Hatschekstraße"
    },
    {
        "kurzbezeichnung": "Hauptstraße",
        "id": 30068,
        "strassenbezeichnung": "Hauptstraße"
    },
    {
        "kurzbezeichnung": "Höhenweg",
        "id": 30069,
        "strassenbezeichnung": "Höhenweg"
    },
    {
        "kurzbezeichnung": "Industriegebiet",
        "id": 16497,
        "strassenbezeichnung": "Industriegebiet"
    },
    {
        "kurzbezeichnung": "Johannes-Honterus-Str.",
        "id": 30070,
        "strassenbezeichnung": "Johannes-Honterus-Straße"
    },
    {
        "kurzbezeichnung": "Julius-Wimmer-Straße",
        "id": 30072,
        "strassenbezeichnung": "Julius-Wimmer-Straße"
    },
    {
        "kurzbezeichnung": "Kapellenweg",
        "id": 30073,
        "strassenbezeichnung": "Kapellenweg"
    },
    {
        "kurzbezeichnung": "Kastingerstraße",
        "id": 96271,
        "strassenbezeichnung": "Kastingerstraße"
    },
    {
        "kurzbezeichnung": "Kettlleiten",
        "id": 74853,
        "strassenbezeichnung": "Kettlleiten"
    },
    {
        "kurzbezeichnung": "Kirchenplatz",
        "id": 30074,
        "strassenbezeichnung": "Kirchenplatz"
    },
    {
        "kurzbezeichnung": "Kleinmüllerstraße",
        "id": 96173,
        "strassenbezeichnung": "Kleinmüllerstraße"
    },
    {
        "kurzbezeichnung": "Koaserweg",
        "id": 30075,
        "strassenbezeichnung": "Koaserweg"
    },
    {
        "kurzbezeichnung": "Königswiese",
        "id": 16488,
        "strassenbezeichnung": "Königswiese"
    },
    {
        "kurzbezeichnung": "Kornfeldweg",
        "id": 109615,
        "strassenbezeichnung": "Kornfeldweg"
    },
    {
        "kurzbezeichnung": "Langauweg",
        "id": 30076,
        "strassenbezeichnung": "Langauweg"
    },
    {
        "kurzbezeichnung": "Leharweg",
        "id": 30077,
        "strassenbezeichnung": "Leharweg"
    },
    {
        "kurzbezeichnung": "Lerchenweg",
        "id": 52339,
        "strassenbezeichnung": "Lerchenweg"
    },
    {
        "kurzbezeichnung": "Maria-Theresia-Straße",
        "id": 30078,
        "strassenbezeichnung": "Maria-Theresia-Straße"
    },
    {
        "kurzbezeichnung": "Martin-Luther-Straße",
        "id": 67300,
        "strassenbezeichnung": "Martin-Luther-Straße"
    },
    {
        "kurzbezeichnung": "Michaelbeuernstraße",
        "id": 92712,
        "strassenbezeichnung": "Michaelbeuernstraße"
    },
    {
        "kurzbezeichnung": "Müllnerweg",
        "id": 30079,
        "strassenbezeichnung": "Müllnerweg"
    },
    {
        "kurzbezeichnung": "Neißinger Straße",
        "id": 30080,
        "strassenbezeichnung": "Neißinger Straße"
    },
    {
        "kurzbezeichnung": "Nösner Straße",
        "id": 102295,
        "strassenbezeichnung": "Nösner Straße"
    },
    {
        "kurzbezeichnung": "Paul-Wiener-Straße",
        "id": 96171,
        "strassenbezeichnung": "Paul-Wiener-Straße"
    },
    {
        "kurzbezeichnung": "Pfar.-M.-Schuster-Pl.",
        "id": 92312,
        "strassenbezeichnung": "Pfarrer-Matthias-Schuster-Platz"
    },
    {
        "kurzbezeichnung": "Promenade",
        "id": 30081,
        "strassenbezeichnung": "Promenade"
    },
    {
        "kurzbezeichnung": "Rathausplatz",
        "id": 30082,
        "strassenbezeichnung": "Rathausplatz"
    },
    {
        "kurzbezeichnung": "Reichersberger Straße",
        "id": 30083,
        "strassenbezeichnung": "Reichersberger Straße"
    },
    {
        "kurzbezeichnung": "Roseggerstraße",
        "id": 30084,
        "strassenbezeichnung": "Roseggerstraße"
    },
    {
        "kurzbezeichnung": "Sachsenstraße",
        "id": 30085,
        "strassenbezeichnung": "Sachsenstraße"
    },
    {
        "kurzbezeichnung": "S.-v.-Brukenthal-Str.",
        "id": 30086,
        "strassenbezeichnung": "Samuel-von-Brukenthal-Straße"
    },
    {
        "kurzbezeichnung": "Schlosserberg",
        "id": 75789,
        "strassenbezeichnung": "Schlosserberg"
    },
    {
        "kurzbezeichnung": "Schulweg",
        "id": 30087,
        "strassenbezeichnung": "Schulweg"
    },
    {
        "kurzbezeichnung": "Seyrlstraße",
        "id": 30088,
        "strassenbezeichnung": "Seyrlstraße"
    },
    {
        "kurzbezeichnung": "Siebenmühlenweg",
        "id": 30089,
        "strassenbezeichnung": "Siebenmühlenweg"
    },
    {
        "kurzbezeichnung": "Sonnleitenweg",
        "id": 55423,
        "strassenbezeichnung": "Sonnleitenweg"
    },
    {
        "kurzbezeichnung": "Sportplatzstraße",
        "id": 96172,
        "strassenbezeichnung": "Sportplatzstraße"
    },
    {
        "kurzbezeichnung": "Steindorfer Straße",
        "id": 30091,
        "strassenbezeichnung": "Steindorfer Straße"
    },
    {
        "kurzbezeichnung": "Stephan-L.-Roth-Pl.",
        "id": 30092,
        "strassenbezeichnung": "Stephan-Ludwig-Roth-Platz"
    },
    {
        "kurzbezeichnung": "Stephan-L.-Roth-Str.",
        "id": 30093,
        "strassenbezeichnung": "Stephan-Ludwig-Roth-Straße"
    },
    {
        "kurzbezeichnung": "Teichstraße",
        "id": 95802,
        "strassenbezeichnung": "Teichstraße"
    },
    {
        "kurzbezeichnung": "Toleranzstraße",
        "id": 30094,
        "strassenbezeichnung": "Toleranzstraße"
    },
    {
        "kurzbezeichnung": "Waldweg",
        "id": 30095,
        "strassenbezeichnung": "Waldweg"
    }
]