[
    {
        "kurzbezeichnung": "Fressenberg",
        "id": 88928,
        "strassenbezeichnung": "Fressenberg"
    },
    {
        "kurzbezeichnung": "Hangweg",
        "id": 117099,
        "strassenbezeichnung": "Hangweg"
    },
    {
        "kurzbezeichnung": "Panoramaweg",
        "id": 117101,
        "strassenbezeichnung": "Panoramaweg"
    },
    {
        "kurzbezeichnung": "Waldweg",
        "id": 117102,
        "strassenbezeichnung": "Waldweg"
    },
    {
        "kurzbezeichnung": "Wasserleitherstraße",
        "id": 117103,
        "strassenbezeichnung": "Wasserleitherstraße"
    },
    {
        "kurzbezeichnung": "Weinmeisterweg",
        "id": 117104,
        "strassenbezeichnung": "Weinmeisterweg"
    },
    {
        "kurzbezeichnung": "Moarweg",
        "id": 117100,
        "strassenbezeichnung": "Moarweg"
    }
]