[
    {
        "kurzbezeichnung": "Am Feld",
        "id": 64320,
        "strassenbezeichnung": "Am Feld"
    },
    {
        "kurzbezeichnung": "Am Sonnhügel",
        "id": 7150,
        "strassenbezeichnung": "Am Sonnhügel"
    },
    {
        "kurzbezeichnung": "Auenweg",
        "id": 7151,
        "strassenbezeichnung": "Auenweg"
    },
    {
        "kurzbezeichnung": "Bachstraße",
        "id": 7153,
        "strassenbezeichnung": "Bachstraße"
    },
    {
        "kurzbezeichnung": "Badeweg",
        "id": 7155,
        "strassenbezeichnung": "Badeweg"
    },
    {
        "kurzbezeichnung": "Bahnhofweg",
        "id": 7157,
        "strassenbezeichnung": "Bahnhofweg"
    },
    {
        "kurzbezeichnung": "Birkenweg",
        "id": 53089,
        "strassenbezeichnung": "Birkenweg"
    },
    {
        "kurzbezeichnung": "Blumenweg",
        "id": 53792,
        "strassenbezeichnung": "Blumenweg"
    },
    {
        "kurzbezeichnung": "Dietrichsteinerstraße",
        "id": 7162,
        "strassenbezeichnung": "Dietrichsteinerstraße"
    },
    {
        "kurzbezeichnung": "Dorfweg",
        "id": 7164,
        "strassenbezeichnung": "Dorfweg"
    },
    {
        "kurzbezeichnung": "Erlenweg",
        "id": 7166,
        "strassenbezeichnung": "Erlenweg"
    },
    {
        "kurzbezeichnung": "Faaker-See-Insel",
        "id": 6595,
        "strassenbezeichnung": "Faaker-See-Insel"
    },
    {
        "kurzbezeichnung": "Faaker-See-Straße",
        "id": 53795,
        "strassenbezeichnung": "Faaker-See-Straße"
    },
    {
        "kurzbezeichnung": "Feldgasse",
        "id": 53090,
        "strassenbezeichnung": "Feldgasse"
    },
    {
        "kurzbezeichnung": "Fischerweg",
        "id": 63866,
        "strassenbezeichnung": "Fischerweg"
    },
    {
        "kurzbezeichnung": "Fliederweg",
        "id": 7171,
        "strassenbezeichnung": "Fliederweg"
    },
    {
        "kurzbezeichnung": "Flurweg",
        "id": 7172,
        "strassenbezeichnung": "Flurweg"
    },
    {
        "kurzbezeichnung": "Föhrenweg",
        "id": 63867,
        "strassenbezeichnung": "Föhrenweg"
    },
    {
        "kurzbezeichnung": "Gartenweg",
        "id": 7175,
        "strassenbezeichnung": "Gartenweg"
    },
    {
        "kurzbezeichnung": "Grünwaldweg",
        "id": 53800,
        "strassenbezeichnung": "Grünwaldweg"
    },
    {
        "kurzbezeichnung": "Halbinselstraße",
        "id": 7177,
        "strassenbezeichnung": "Halbinselstraße"
    },
    {
        "kurzbezeichnung": "Hangweg",
        "id": 7178,
        "strassenbezeichnung": "Hangweg"
    },
    {
        "kurzbezeichnung": "Inselweg",
        "id": 7184,
        "strassenbezeichnung": "Inselweg"
    },
    {
        "kurzbezeichnung": "Karawankenweg",
        "id": 7187,
        "strassenbezeichnung": "Karawankenweg"
    },
    {
        "kurzbezeichnung": "Kirchenweg",
        "id": 7190,
        "strassenbezeichnung": "Kirchenweg"
    },
    {
        "kurzbezeichnung": "Kirchgasse",
        "id": 7191,
        "strassenbezeichnung": "Kirchgasse"
    },
    {
        "kurzbezeichnung": "Kornblumenweg",
        "id": -30782,
        "strassenbezeichnung": "Kornblumenweg"
    },
    {
        "kurzbezeichnung": "Kornweg",
        "id": 63868,
        "strassenbezeichnung": "Kornweg"
    },
    {
        "kurzbezeichnung": "Mallestigerstraße",
        "id": 7195,
        "strassenbezeichnung": "Mallestigerstraße"
    },
    {
        "kurzbezeichnung": "Margaritenweg",
        "id": 67057,
        "strassenbezeichnung": "Margaritenweg"
    },
    {
        "kurzbezeichnung": "Marktplatz",
        "id": 75588,
        "strassenbezeichnung": "Marktplatz"
    },
    {
        "kurzbezeichnung": "Molkereistraße",
        "id": 7197,
        "strassenbezeichnung": "Molkereistraße"
    },
    {
        "kurzbezeichnung": "Mühlenweg",
        "id": 7198,
        "strassenbezeichnung": "Mühlenweg"
    },
    {
        "kurzbezeichnung": "Parkweg",
        "id": 53809,
        "strassenbezeichnung": "Parkweg"
    },
    {
        "kurzbezeichnung": "Sankt Stefaner Weg",
        "id": 7212,
        "strassenbezeichnung": "Sankt Stefaner Weg"
    },
    {
        "kurzbezeichnung": "Sauernigweg",
        "id": 7204,
        "strassenbezeichnung": "Sauernigweg"
    },
    {
        "kurzbezeichnung": "Schilfsteig",
        "id": 49833,
        "strassenbezeichnung": "Schilfsteig"
    },
    {
        "kurzbezeichnung": "Seestraße",
        "id": 7207,
        "strassenbezeichnung": "Seestraße"
    },
    {
        "kurzbezeichnung": "Seeufer-Landesstraße",
        "id": 7208,
        "strassenbezeichnung": "Seeufer-Landesstraße"
    },
    {
        "kurzbezeichnung": "Seeweg",
        "id": 53814,
        "strassenbezeichnung": "Seeweg"
    },
    {
        "kurzbezeichnung": "Seewiese",
        "id": 113556,
        "strassenbezeichnung": "Seewiese"
    },
    {
        "kurzbezeichnung": "Siedlerweg",
        "id": 7209,
        "strassenbezeichnung": "Siedlerweg"
    },
    {
        "kurzbezeichnung": "Strand-Nord",
        "id": 7213,
        "strassenbezeichnung": "Strand-Nord"
    },
    {
        "kurzbezeichnung": "Strandweg",
        "id": 7214,
        "strassenbezeichnung": "Strandweg"
    },
    {
        "kurzbezeichnung": "Uferweg",
        "id": 7215,
        "strassenbezeichnung": "Uferweg"
    },
    {
        "kurzbezeichnung": "Waldsiedlung",
        "id": 7220,
        "strassenbezeichnung": "Waldsiedlung"
    },
    {
        "kurzbezeichnung": "Wiesengrund",
        "id": 75212,
        "strassenbezeichnung": "Wiesengrund"
    }
]