[
    {
        "kurzbezeichnung": "Auf dem Kikel",
        "id": 7234,
        "strassenbezeichnung": "Auf dem Kikel"
    },
    {
        "kurzbezeichnung": "Dueler Straße",
        "id": 7256,
        "strassenbezeichnung": "Dueler Straße"
    },
    {
        "kurzbezeichnung": "Fliehburgweg",
        "id": 7264,
        "strassenbezeichnung": "Fliehburgweg"
    },
    {
        "kurzbezeichnung": "Grabenweg",
        "id": 7270,
        "strassenbezeichnung": "Grabenweg"
    },
    {
        "kurzbezeichnung": "Weißenbachweg",
        "id": 101486,
        "strassenbezeichnung": "Weißenbachweg"
    }
]