[
    {
        "kurzbezeichnung": "Alter Platz",
        "id": 4163,
        "strassenbezeichnung": "Alter Platz"
    },
    {
        "kurzbezeichnung": "Alte-Rathaus-Gasse",
        "id": 59027,
        "strassenbezeichnung": "Alte-Rathaus-Gasse"
    },
    {
        "kurzbezeichnung": "Eisengasse",
        "id": 102711,
        "strassenbezeichnung": "Eisengasse"
    },
    {
        "kurzbezeichnung": "Glasergasse",
        "id": 4430,
        "strassenbezeichnung": "Glasergasse"
    },
    {
        "kurzbezeichnung": "Goethepark",
        "id": 4433,
        "strassenbezeichnung": "Goethepark"
    },
    {
        "kurzbezeichnung": "Herrengasse",
        "id": 4508,
        "strassenbezeichnung": "Herrengasse"
    },
    {
        "kurzbezeichnung": "Johann-Thys-Zeile",
        "id": 4551,
        "strassenbezeichnung": "Johann-Thys-Zeile"
    },
    {
        "kurzbezeichnung": "Josef-W.-Dobernig-Str.",
        "id": 4534,
        "strassenbezeichnung": "Josef-Wolfgang-Dobernig-Straße"
    },
    {
        "kurzbezeichnung": "Kiki-Kogelnik-Gasse",
        "id": 96001,
        "strassenbezeichnung": "Kiki-Kogelnik-Gasse"
    },
    {
        "kurzbezeichnung": "Klostergasse",
        "id": 4616,
        "strassenbezeichnung": "Klostergasse"
    },
    {
        "kurzbezeichnung": "Landhaushof",
        "id": 4659,
        "strassenbezeichnung": "Landhaushof"
    },
    {
        "kurzbezeichnung": "Neuer Platz",
        "id": 4769,
        "strassenbezeichnung": "Neuer Platz"
    },
    {
        "kurzbezeichnung": "Norbert-Artner-Park",
        "id": 96019,
        "strassenbezeichnung": "Norbert-Artner-Park"
    },
    {
        "kurzbezeichnung": "Pfarrhofgasse",
        "id": 4815,
        "strassenbezeichnung": "Pfarrhofgasse"
    },
    {
        "kurzbezeichnung": "Pfarrplatz",
        "id": 4816,
        "strassenbezeichnung": "Pfarrplatz"
    },
    {
        "kurzbezeichnung": "Purtscherstraße",
        "id": 4846,
        "strassenbezeichnung": "Purtscherstraße"
    },
    {
        "kurzbezeichnung": "Reitschulgasse",
        "id": 4874,
        "strassenbezeichnung": "Reitschulgasse"
    },
    {
        "kurzbezeichnung": "St. Veiter Ring",
        "id": 4989,
        "strassenbezeichnung": "St. Veiter Ring"
    },
    {
        "kurzbezeichnung": "Tabakgasse",
        "id": 59066,
        "strassenbezeichnung": "Tabakgasse"
    },
    {
        "kurzbezeichnung": "Theatergasse",
        "id": 5034,
        "strassenbezeichnung": "Theatergasse"
    },
    {
        "kurzbezeichnung": "Theaterplatz",
        "id": 5035,
        "strassenbezeichnung": "Theaterplatz"
    },
    {
        "kurzbezeichnung": "Ursulinengasse",
        "id": 5065,
        "strassenbezeichnung": "Ursulinengasse"
    },
    {
        "kurzbezeichnung": "Villacher Straße",
        "id": 5079,
        "strassenbezeichnung": "Villacher Straße"
    },
    {
        "kurzbezeichnung": "Eggergasse",
        "id": -18752,
        "strassenbezeichnung": "Eggergasse"
    },
    {
        "kurzbezeichnung": "Goessgasse",
        "id": -18753,
        "strassenbezeichnung": "Goessgasse"
    },
    {
        "kurzbezeichnung": "Heiligengeistplatz",
        "id": 4493,
        "strassenbezeichnung": "Heiligengeistplatz"
    },
    {
        "kurzbezeichnung": "Heiligengeistschütt",
        "id": -18754,
        "strassenbezeichnung": "Heiligengeistschütt"
    },
    {
        "kurzbezeichnung": "Heuplatz",
        "id": 4514,
        "strassenbezeichnung": "Heuplatz"
    },
    {
        "kurzbezeichnung": "Kramergasse",
        "id": 4635,
        "strassenbezeichnung": "Kramergasse"
    },
    {
        "kurzbezeichnung": "St. Veiter Straße",
        "id": 4990,
        "strassenbezeichnung": "St. Veiter Straße"
    },
    {
        "kurzbezeichnung": "Stauderplatz",
        "id": 4994,
        "strassenbezeichnung": "Stauderplatz"
    },
    {
        "kurzbezeichnung": "Wiener Gasse",
        "id": 5122,
        "strassenbezeichnung": "Wiener Gasse"
    }
]