[
    {
        "kurzbezeichnung": "Aubergerstraße",
        "id": 63622,
        "strassenbezeichnung": "Aubergerstraße"
    },
    {
        "kurzbezeichnung": "Bachstraße",
        "id": 12562,
        "strassenbezeichnung": "Bachstraße"
    },
    {
        "kurzbezeichnung": "Berggasse",
        "id": 12564,
        "strassenbezeichnung": "Berggasse"
    },
    {
        "kurzbezeichnung": "Dechant Neidl-Gasse",
        "id": 12569,
        "strassenbezeichnung": "Dechant Neidl-Gasse"
    },
    {
        "kurzbezeichnung": "Feldgasse",
        "id": 50615,
        "strassenbezeichnung": "Feldgasse"
    },
    {
        "kurzbezeichnung": "Hauptstraße",
        "id": 50617,
        "strassenbezeichnung": "Hauptstraße"
    },
    {
        "kurzbezeichnung": "Hochweg",
        "id": 95061,
        "strassenbezeichnung": "Hochweg"
    },
    {
        "kurzbezeichnung": "Hohlweg",
        "id": 12580,
        "strassenbezeichnung": "Hohlweg"
    },
    {
        "kurzbezeichnung": "Kellerberg",
        "id": 113492,
        "strassenbezeichnung": "Kellerberg"
    },
    {
        "kurzbezeichnung": "Kirchenberg",
        "id": 104224,
        "strassenbezeichnung": "Kirchenberg"
    },
    {
        "kurzbezeichnung": "Lindenweg",
        "id": 70963,
        "strassenbezeichnung": "Lindenweg"
    },
    {
        "kurzbezeichnung": "Matzner Straße",
        "id": 50619,
        "strassenbezeichnung": "Matzner Straße"
    },
    {
        "kurzbezeichnung": "Probstenzeil",
        "id": 12599,
        "strassenbezeichnung": "Probstenzeil"
    },
    {
        "kurzbezeichnung": "Raggendorfer Zeil",
        "id": 12600,
        "strassenbezeichnung": "Raggendorfer Zeil"
    },
    {
        "kurzbezeichnung": "Schottenweg",
        "id": 12608,
        "strassenbezeichnung": "Schottenweg"
    },
    {
        "kurzbezeichnung": "Zur Viehtrift",
        "id": 12627,
        "strassenbezeichnung": "Zur Viehtrift"
    }
]