[
    {
        "kurzbezeichnung": "Alter Postweg",
        "id": 98343,
        "strassenbezeichnung": "Alter Postweg"
    },
    {
        "kurzbezeichnung": "Am Berg",
        "id": 98344,
        "strassenbezeichnung": "Am Berg"
    },
    {
        "kurzbezeichnung": "Am Mühlbach",
        "id": 98345,
        "strassenbezeichnung": "Am Mühlbach"
    },
    {
        "kurzbezeichnung": "Am Pfarrberg",
        "id": 98346,
        "strassenbezeichnung": "Am Pfarrberg"
    },
    {
        "kurzbezeichnung": "Anton Hackler-Gasse",
        "id": 98347,
        "strassenbezeichnung": "Anton Hackler-Gasse"
    },
    {
        "kurzbezeichnung": "Atzelsdorferstraße",
        "id": 98348,
        "strassenbezeichnung": "Atzelsdorferstraße"
    },
    {
        "kurzbezeichnung": "Dr. Stur-Straße",
        "id": 98351,
        "strassenbezeichnung": "Dr. Stur-Straße"
    },
    {
        "kurzbezeichnung": "Fünfhaus",
        "id": 98352,
        "strassenbezeichnung": "Fünfhaus"
    },
    {
        "kurzbezeichnung": "Graf Perlas-Straße",
        "id": 98353,
        "strassenbezeichnung": "Graf Perlas-Straße"
    },
    {
        "kurzbezeichnung": "Gutshofstraße",
        "id": 98354,
        "strassenbezeichnung": "Gutshofstraße"
    },
    {
        "kurzbezeichnung": "Im Pfarrergassl",
        "id": 98355,
        "strassenbezeichnung": "Im Pfarrergassl"
    },
    {
        "kurzbezeichnung": "Josef Wegert-Straße",
        "id": 98322,
        "strassenbezeichnung": "Josef Wegert-Straße"
    },
    {
        "kurzbezeichnung": "Josefs-Brunnen Gasse",
        "id": 98323,
        "strassenbezeichnung": "Josefs-Brunnen Gasse"
    },
    {
        "kurzbezeichnung": "Kainzstraße",
        "id": 98324,
        "strassenbezeichnung": "Kainzstraße"
    },
    {
        "kurzbezeichnung": "Karl König-Straße",
        "id": 98325,
        "strassenbezeichnung": "Karl König-Straße"
    },
    {
        "kurzbezeichnung": "Kastanienallee",
        "id": 98326,
        "strassenbezeichnung": "Kastanienallee"
    },
    {
        "kurzbezeichnung": "Kirschenallee",
        "id": 98328,
        "strassenbezeichnung": "Kirschenallee"
    },
    {
        "kurzbezeichnung": "Lanzendorfer Hauptstr.",
        "id": 55602,
        "strassenbezeichnung": "Lanzendorfer Hauptstraße"
    },
    {
        "kurzbezeichnung": "Obere Hauptstraße",
        "id": 98331,
        "strassenbezeichnung": "Obere Hauptstraße"
    },
    {
        "kurzbezeichnung": "Schloßzeile",
        "id": 98334,
        "strassenbezeichnung": "Schloßzeile"
    },
    {
        "kurzbezeichnung": "Schwemmzeile",
        "id": 98335,
        "strassenbezeichnung": "Schwemmzeile"
    },
    {
        "kurzbezeichnung": "Theresia Weiß-Ring",
        "id": 93939,
        "strassenbezeichnung": "Theresia Weiß-Ring"
    },
    {
        "kurzbezeichnung": "Untere Hauptstraße",
        "id": 98337,
        "strassenbezeichnung": "Untere Hauptstraße"
    },
    {
        "kurzbezeichnung": "Zu den Linden",
        "id": 98339,
        "strassenbezeichnung": "Zu den Linden"
    },
    {
        "kurzbezeichnung": "Zur Freyung",
        "id": 98340,
        "strassenbezeichnung": "Zur Freyung"
    },
    {
        "kurzbezeichnung": "Zur Kirche",
        "id": 98341,
        "strassenbezeichnung": "Zur Kirche"
    },
    {
        "kurzbezeichnung": "Ernstbrunnerstraße",
        "id": 6333,
        "strassenbezeichnung": "Ernstbrunnerstraße"
    },
    {
        "kurzbezeichnung": "Kellerrundplatz",
        "id": -32657,
        "strassenbezeichnung": "Kellerrundplatz"
    }
]