[
    {
        "kurzbezeichnung": "Akazienweg",
        "id": 113089,
        "strassenbezeichnung": "Akazienweg"
    },
    {
        "kurzbezeichnung": "Am Sonnenberg",
        "id": 113090,
        "strassenbezeichnung": "Am Sonnenberg"
    },
    {
        "kurzbezeichnung": "Bachgasse",
        "id": 113091,
        "strassenbezeichnung": "Bachgasse"
    },
    {
        "kurzbezeichnung": "Beim Ziehbrunnen",
        "id": 113092,
        "strassenbezeichnung": "Beim Ziehbrunnen"
    },
    {
        "kurzbezeichnung": "Bergen",
        "id": 113093,
        "strassenbezeichnung": "Bergen"
    },
    {
        "kurzbezeichnung": "Biotopweg",
        "id": 113094,
        "strassenbezeichnung": "Biotopweg"
    },
    {
        "kurzbezeichnung": "Birkengasse",
        "id": 113095,
        "strassenbezeichnung": "Birkengasse"
    },
    {
        "kurzbezeichnung": "Brodac",
        "id": 113096,
        "strassenbezeichnung": "Brodac"
    },
    {
        "kurzbezeichnung": "Brückengasse",
        "id": 113097,
        "strassenbezeichnung": "Brückengasse"
    },
    {
        "kurzbezeichnung": "Feldgasse",
        "id": 113098,
        "strassenbezeichnung": "Feldgasse"
    },
    {
        "kurzbezeichnung": "Fichtenweg",
        "id": 113099,
        "strassenbezeichnung": "Fichtenweg"
    },
    {
        "kurzbezeichnung": "Florianigasse",
        "id": 113100,
        "strassenbezeichnung": "Florianigasse"
    },
    {
        "kurzbezeichnung": "Friedhofgasse",
        "id": 113101,
        "strassenbezeichnung": "Friedhofgasse"
    },
    {
        "kurzbezeichnung": "Gartengasse",
        "id": 113102,
        "strassenbezeichnung": "Gartengasse"
    },
    {
        "kurzbezeichnung": "Hauptplatz",
        "id": 113103,
        "strassenbezeichnung": "Hauptplatz"
    },
    {
        "kurzbezeichnung": "Jägergasse",
        "id": 113104,
        "strassenbezeichnung": "Jägergasse"
    },
    {
        "kurzbezeichnung": "Kaiserweg",
        "id": 113105,
        "strassenbezeichnung": "Kaiserweg"
    },
    {
        "kurzbezeichnung": "Kirchenweg",
        "id": 113107,
        "strassenbezeichnung": "Kirchenweg"
    },
    {
        "kurzbezeichnung": "Kleinfavoriten",
        "id": 113108,
        "strassenbezeichnung": "Kleinfavoriten"
    },
    {
        "kurzbezeichnung": "Lenzhäuser",
        "id": 113109,
        "strassenbezeichnung": "Lenzhäuser"
    },
    {
        "kurzbezeichnung": "Lindenweg",
        "id": 113110,
        "strassenbezeichnung": "Lindenweg"
    },
    {
        "kurzbezeichnung": "Martinigasse",
        "id": 113111,
        "strassenbezeichnung": "Martinigasse"
    },
    {
        "kurzbezeichnung": "Matthias Semeliker G.",
        "id": 113112,
        "strassenbezeichnung": "Matthias Semeliker Gasse"
    },
    {
        "kurzbezeichnung": "Neue Gasse",
        "id": 116255,
        "strassenbezeichnung": "Neue Gasse"
    },
    {
        "kurzbezeichnung": "Obere Hauptstraße",
        "id": 113113,
        "strassenbezeichnung": "Obere Hauptstraße"
    },
    {
        "kurzbezeichnung": "Schmale Gasse",
        "id": 113114,
        "strassenbezeichnung": "Schmale Gasse"
    },
    {
        "kurzbezeichnung": "Tublweg",
        "id": 113115,
        "strassenbezeichnung": "Tublweg"
    },
    {
        "kurzbezeichnung": "Untere Hauptstraße",
        "id": 113116,
        "strassenbezeichnung": "Untere Hauptstraße"
    },
    {
        "kurzbezeichnung": "Waldgasse",
        "id": 113117,
        "strassenbezeichnung": "Waldgasse"
    },
    {
        "kurzbezeichnung": "Weidengasse",
        "id": 113118,
        "strassenbezeichnung": "Weidengasse"
    },
    {
        "kurzbezeichnung": "Wiesengasse",
        "id": 113119,
        "strassenbezeichnung": "Wiesengasse"
    },
    {
        "kurzbezeichnung": "Winkelweg",
        "id": 113120,
        "strassenbezeichnung": "Winkelweg"
    }
]