[
    {
        "kurzbezeichnung": "Bierweg",
        "id": 25987,
        "strassenbezeichnung": "Bierweg"
    },
    {
        "kurzbezeichnung": "Dr.Stadler Gasse",
        "id": 25990,
        "strassenbezeichnung": "Dr.Stadler Gasse"
    },
    {
        "kurzbezeichnung": "Fischmarkt",
        "id": 25993,
        "strassenbezeichnung": "Fischmarkt"
    },
    {
        "kurzbezeichnung": "Hofmarkt",
        "id": 26004,
        "strassenbezeichnung": "Hofmarkt"
    },
    {
        "kurzbezeichnung": "Kühdobl",
        "id": 26037,
        "strassenbezeichnung": "Kühdobl"
    },
    {
        "kurzbezeichnung": "Pfarrgrund",
        "id": 26062,
        "strassenbezeichnung": "Pfarrgrund"
    },
    {
        "kurzbezeichnung": "Pramerstraße",
        "id": 26079,
        "strassenbezeichnung": "Pramerstraße"
    },
    {
        "kurzbezeichnung": "Riedauerstraße",
        "id": 26090,
        "strassenbezeichnung": "Riedauerstraße"
    },
    {
        "kurzbezeichnung": "Riederstraße",
        "id": 26102,
        "strassenbezeichnung": "Riederstraße"
    },
    {
        "kurzbezeichnung": "Schulstraße",
        "id": 47531,
        "strassenbezeichnung": "Schulstraße"
    },
    {
        "kurzbezeichnung": "Südhang",
        "id": 47534,
        "strassenbezeichnung": "Südhang"
    },
    {
        "kurzbezeichnung": "Teichstraße",
        "id": 47542,
        "strassenbezeichnung": "Teichstraße"
    },
    {
        "kurzbezeichnung": "Sittling",
        "id": 84676,
        "strassenbezeichnung": "Sittling"
    },
    {
        "kurzbezeichnung": "Aichet",
        "id": 84903,
        "strassenbezeichnung": "Aichet"
    },
    {
        "kurzbezeichnung": "Altmannsdorf",
        "id": 84904,
        "strassenbezeichnung": "Altmannsdorf"
    },
    {
        "kurzbezeichnung": "Arling",
        "id": 84905,
        "strassenbezeichnung": "Arling"
    },
    {
        "kurzbezeichnung": "Baumgarten",
        "id": 84906,
        "strassenbezeichnung": "Baumgarten"
    },
    {
        "kurzbezeichnung": "Brandstätten",
        "id": 84907,
        "strassenbezeichnung": "Brandstätten"
    },
    {
        "kurzbezeichnung": "Breitenried",
        "id": 84908,
        "strassenbezeichnung": "Breitenried"
    },
    {
        "kurzbezeichnung": "Bruckleiten",
        "id": 84909,
        "strassenbezeichnung": "Bruckleiten"
    },
    {
        "kurzbezeichnung": "Edtleiten",
        "id": 84910,
        "strassenbezeichnung": "Edtleiten"
    },
    {
        "kurzbezeichnung": "Ellerbach",
        "id": 84911,
        "strassenbezeichnung": "Ellerbach"
    },
    {
        "kurzbezeichnung": "Flohleiten",
        "id": 84912,
        "strassenbezeichnung": "Flohleiten"
    },
    {
        "kurzbezeichnung": "Gansing",
        "id": 84913,
        "strassenbezeichnung": "Gansing"
    },
    {
        "kurzbezeichnung": "Gotthalmsedt",
        "id": 84914,
        "strassenbezeichnung": "Gotthalmsedt"
    },
    {
        "kurzbezeichnung": "Günzing",
        "id": 84915,
        "strassenbezeichnung": "Günzing"
    },
    {
        "kurzbezeichnung": "Helfingsdorf",
        "id": 84916,
        "strassenbezeichnung": "Helfingsdorf"
    },
    {
        "kurzbezeichnung": "Hohenerlach",
        "id": 84917,
        "strassenbezeichnung": "Hohenerlach"
    },
    {
        "kurzbezeichnung": "Jebing",
        "id": 84918,
        "strassenbezeichnung": "Jebing"
    },
    {
        "kurzbezeichnung": "Jedretsberg",
        "id": 84919,
        "strassenbezeichnung": "Jedretsberg"
    },
    {
        "kurzbezeichnung": "Kainzing",
        "id": 84920,
        "strassenbezeichnung": "Kainzing"
    },
    {
        "kurzbezeichnung": "Kleingaisbach",
        "id": 84921,
        "strassenbezeichnung": "Kleingaisbach"
    },
    {
        "kurzbezeichnung": "Lacken",
        "id": 84922,
        "strassenbezeichnung": "Lacken"
    },
    {
        "kurzbezeichnung": "Petersham",
        "id": 84924,
        "strassenbezeichnung": "Petersham"
    },
    {
        "kurzbezeichnung": "Pimingsdorf",
        "id": 84925,
        "strassenbezeichnung": "Pimingsdorf"
    },
    {
        "kurzbezeichnung": "Sittling",
        "id": 84927,
        "strassenbezeichnung": "Sittling"
    },
    {
        "kurzbezeichnung": "Tiefenbach",
        "id": 84928,
        "strassenbezeichnung": "Tiefenbach"
    },
    {
        "kurzbezeichnung": "Wiesenberg",
        "id": 84929,
        "strassenbezeichnung": "Wiesenberg"
    },
    {
        "kurzbezeichnung": "Wietraun",
        "id": 84930,
        "strassenbezeichnung": "Wietraun"
    },
    {
        "kurzbezeichnung": "Wohleiten",
        "id": 84931,
        "strassenbezeichnung": "Wohleiten"
    },
    {
        "kurzbezeichnung": "Wolfsedt",
        "id": 84932,
        "strassenbezeichnung": "Wolfsedt"
    },
    {
        "kurzbezeichnung": "Zahra",
        "id": 84933,
        "strassenbezeichnung": "Zahra"
    },
    {
        "kurzbezeichnung": "Wiesenhang",
        "id": 104337,
        "strassenbezeichnung": "Wiesenhang"
    },
    {
        "kurzbezeichnung": "Sonnleiten",
        "id": 105056,
        "strassenbezeichnung": "Sonnleiten"
    },
    {
        "kurzbezeichnung": "Unterbreitenried",
        "id": 105057,
        "strassenbezeichnung": "Unterbreitenried"
    },
    {
        "kurzbezeichnung": "Lindet",
        "id": 105058,
        "strassenbezeichnung": "Lindet"
    }
]