[
    {
        "kurzbezeichnung": "Fugging",
        "id": -32402,
        "strassenbezeichnung": "Fugging"
    },
    {
        "kurzbezeichnung": "Rosenweg",
        "id": -32331,
        "strassenbezeichnung": "Rosenweg "
    },
    {
        "kurzbezeichnung": "Rosenweg",
        "id": -32330,
        "strassenbezeichnung": "Rosenweg"
    },
    {
        "kurzbezeichnung": "Tulpenweg",
        "id": -32162,
        "strassenbezeichnung": "Tulpenweg"
    },
    {
        "kurzbezeichnung": "Am Anger",
        "id": 59236,
        "strassenbezeichnung": "Am Anger"
    },
    {
        "kurzbezeichnung": "Mühlenstraße",
        "id": 60502,
        "strassenbezeichnung": "Mühlenstraße"
    },
    {
        "kurzbezeichnung": "Moosweg",
        "id": 60503,
        "strassenbezeichnung": "Moosweg"
    },
    {
        "kurzbezeichnung": "Steinbruchweg",
        "id": 60504,
        "strassenbezeichnung": "Steinbruchweg"
    },
    {
        "kurzbezeichnung": "Naglstraße",
        "id": 60505,
        "strassenbezeichnung": "Naglstraße"
    },
    {
        "kurzbezeichnung": "Ettenauerstraße",
        "id": 60508,
        "strassenbezeichnung": "Ettenauerstraße"
    },
    {
        "kurzbezeichnung": "Felmstraße",
        "id": 60513,
        "strassenbezeichnung": "Felmstraße"
    },
    {
        "kurzbezeichnung": "Stellbergweg",
        "id": 60515,
        "strassenbezeichnung": "Stellbergweg"
    },
    {
        "kurzbezeichnung": "Roidhamweg",
        "id": 60519,
        "strassenbezeichnung": "Roidhamweg"
    },
    {
        "kurzbezeichnung": "Obersimling",
        "id": 60520,
        "strassenbezeichnung": "Obersimling"
    },
    {
        "kurzbezeichnung": "Römerstraße",
        "id": 60523,
        "strassenbezeichnung": "Römerstraße"
    },
    {
        "kurzbezeichnung": "Stubmühlenweg",
        "id": 60524,
        "strassenbezeichnung": "Stubmühlenweg"
    },
    {
        "kurzbezeichnung": "Sinzingerstraße",
        "id": 60525,
        "strassenbezeichnung": "Sinzingerstraße"
    },
    {
        "kurzbezeichnung": "Lohen",
        "id": 60526,
        "strassenbezeichnung": "Lohen"
    },
    {
        "kurzbezeichnung": "Weilhartstraße",
        "id": 60602,
        "strassenbezeichnung": "Weilhartstraße"
    },
    {
        "kurzbezeichnung": "Hinterofenstraße",
        "id": 60603,
        "strassenbezeichnung": "Hinterofenstraße"
    },
    {
        "kurzbezeichnung": "Mukenham",
        "id": 60604,
        "strassenbezeichnung": "Mukenham"
    },
    {
        "kurzbezeichnung": "Trimmelkamerstraße",
        "id": 60605,
        "strassenbezeichnung": "Trimmelkamerstraße"
    },
    {
        "kurzbezeichnung": "Bräugasse",
        "id": 60606,
        "strassenbezeichnung": "Bräugasse"
    },
    {
        "kurzbezeichnung": "Alte Landstraße",
        "id": 60607,
        "strassenbezeichnung": "Alte Landstraße"
    },
    {
        "kurzbezeichnung": "Bergstraße",
        "id": 60608,
        "strassenbezeichnung": "Bergstraße"
    },
    {
        "kurzbezeichnung": "Entengasse",
        "id": 60609,
        "strassenbezeichnung": "Entengasse"
    },
    {
        "kurzbezeichnung": "Salzachstraße",
        "id": 60610,
        "strassenbezeichnung": "Salzachstraße"
    },
    {
        "kurzbezeichnung": "Gablmachergasse",
        "id": 60611,
        "strassenbezeichnung": "Gablmachergasse"
    },
    {
        "kurzbezeichnung": "Schmiedgasse",
        "id": 60612,
        "strassenbezeichnung": "Schmiedgasse"
    },
    {
        "kurzbezeichnung": "Mayrwiesgasse",
        "id": 60613,
        "strassenbezeichnung": "Mayrwiesgasse"
    },
    {
        "kurzbezeichnung": "Pfarrweg",
        "id": 60614,
        "strassenbezeichnung": "Pfarrweg"
    },
    {
        "kurzbezeichnung": "Schulstraße",
        "id": 60615,
        "strassenbezeichnung": "Schulstraße"
    },
    {
        "kurzbezeichnung": "Ponzerwiesweg",
        "id": 60616,
        "strassenbezeichnung": "Ponzerwiesweg"
    },
    {
        "kurzbezeichnung": "Kirchgasse",
        "id": 60617,
        "strassenbezeichnung": "Kirchgasse"
    },
    {
        "kurzbezeichnung": "Molkereisiedlung",
        "id": 60618,
        "strassenbezeichnung": "Molkereisiedlung"
    },
    {
        "kurzbezeichnung": "Ziegelei",
        "id": 60619,
        "strassenbezeichnung": "Ziegelei"
    },
    {
        "kurzbezeichnung": "Hochbaumland",
        "id": 60620,
        "strassenbezeichnung": "Hochbaumland"
    },
    {
        "kurzbezeichnung": "Dietrichfeld",
        "id": 60621,
        "strassenbezeichnung": "Dietrichfeld"
    },
    {
        "kurzbezeichnung": "Oberfeld",
        "id": 60622,
        "strassenbezeichnung": "Oberfeld"
    },
    {
        "kurzbezeichnung": "Unterfeld",
        "id": 61445,
        "strassenbezeichnung": "Unterfeld"
    },
    {
        "kurzbezeichnung": "Naglfeld",
        "id": 73724,
        "strassenbezeichnung": "Naglfeld"
    },
    {
        "kurzbezeichnung": "Parkstraße",
        "id": 73725,
        "strassenbezeichnung": "Parkstraße"
    },
    {
        "kurzbezeichnung": "Weißplatz",
        "id": 81871,
        "strassenbezeichnung": "Weißplatz"
    },
    {
        "kurzbezeichnung": "Marktl",
        "id": 81897,
        "strassenbezeichnung": "Marktl"
    },
    {
        "kurzbezeichnung": "Diepoltsdorf",
        "id": 82219,
        "strassenbezeichnung": "Diepoltsdorf"
    },
    {
        "kurzbezeichnung": "Ernsting",
        "id": 82220,
        "strassenbezeichnung": "Ernsting"
    },
    {
        "kurzbezeichnung": "Ettenau",
        "id": 82221,
        "strassenbezeichnung": "Ettenau"
    },
    {
        "kurzbezeichnung": "Felm",
        "id": 82222,
        "strassenbezeichnung": "Felm"
    },
    {
        "kurzbezeichnung": "Gumpling",
        "id": 82223,
        "strassenbezeichnung": "Gumpling"
    },
    {
        "kurzbezeichnung": "Hollersbach",
        "id": 82224,
        "strassenbezeichnung": "Hollersbach"
    },
    {
        "kurzbezeichnung": "Marktl",
        "id": 82225,
        "strassenbezeichnung": "Marktl"
    },
    {
        "kurzbezeichnung": "Simling",
        "id": 82228,
        "strassenbezeichnung": "Simling"
    },
    {
        "kurzbezeichnung": "Sinzing",
        "id": 82229,
        "strassenbezeichnung": "Sinzing"
    },
    {
        "kurzbezeichnung": "Steinbach",
        "id": 82230,
        "strassenbezeichnung": "Steinbach"
    },
    {
        "kurzbezeichnung": "Wimm",
        "id": 82231,
        "strassenbezeichnung": "Wimm"
    },
    {
        "kurzbezeichnung": "Hollersbach",
        "id": 82367,
        "strassenbezeichnung": "Hollersbach"
    },
    {
        "kurzbezeichnung": "Roidham",
        "id": 82374,
        "strassenbezeichnung": "Roidham"
    },
    {
        "kurzbezeichnung": "Eichbichl",
        "id": 82393,
        "strassenbezeichnung": "Eichbichl"
    },
    {
        "kurzbezeichnung": "Hadermarkt",
        "id": 82394,
        "strassenbezeichnung": "Hadermarkt"
    },
    {
        "kurzbezeichnung": "Schwabenlandl",
        "id": 82395,
        "strassenbezeichnung": "Schwabenlandl"
    },
    {
        "kurzbezeichnung": "Werfenau",
        "id": 82396,
        "strassenbezeichnung": "Werfenau"
    },
    {
        "kurzbezeichnung": "Döstling",
        "id": 82453,
        "strassenbezeichnung": "Döstling"
    },
    {
        "kurzbezeichnung": "Eckldorf",
        "id": 82454,
        "strassenbezeichnung": "Eckldorf"
    },
    {
        "kurzbezeichnung": "Ehersdorf",
        "id": 82455,
        "strassenbezeichnung": "Ehersdorf"
    },
    {
        "kurzbezeichnung": "Eichbichl",
        "id": 82456,
        "strassenbezeichnung": "Eichbichl"
    },
    {
        "kurzbezeichnung": "Fucking",
        "id": 82457,
        "strassenbezeichnung": "Fucking"
    },
    {
        "kurzbezeichnung": "Haid",
        "id": 82458,
        "strassenbezeichnung": "Haid"
    },
    {
        "kurzbezeichnung": "Hörndl",
        "id": 82459,
        "strassenbezeichnung": "Hörndl"
    },
    {
        "kurzbezeichnung": "Hofstadt",
        "id": 82460,
        "strassenbezeichnung": "Hofstadt"
    },
    {
        "kurzbezeichnung": "Hofweiden",
        "id": 82461,
        "strassenbezeichnung": "Hofweiden"
    },
    {
        "kurzbezeichnung": "Hucking",
        "id": 82462,
        "strassenbezeichnung": "Hucking"
    },
    {
        "kurzbezeichnung": "Leithen",
        "id": 82463,
        "strassenbezeichnung": "Leithen"
    },
    {
        "kurzbezeichnung": "Ölling",
        "id": 82464,
        "strassenbezeichnung": "Ölling"
    },
    {
        "kurzbezeichnung": "Schmidham",
        "id": 82465,
        "strassenbezeichnung": "Schmidham"
    },
    {
        "kurzbezeichnung": "Sinzing",
        "id": 82466,
        "strassenbezeichnung": "Sinzing"
    },
    {
        "kurzbezeichnung": "Staig",
        "id": 82467,
        "strassenbezeichnung": "Staig"
    },
    {
        "kurzbezeichnung": "Tarsdorf",
        "id": 82468,
        "strassenbezeichnung": "Tarsdorf"
    },
    {
        "kurzbezeichnung": "Wimm",
        "id": 82469,
        "strassenbezeichnung": "Wimm"
    },
    {
        "kurzbezeichnung": "Winham",
        "id": 82470,
        "strassenbezeichnung": "Winham"
    },
    {
        "kurzbezeichnung": "Wolfing",
        "id": 82471,
        "strassenbezeichnung": "Wolfing"
    },
    {
        "kurzbezeichnung": "Wupping",
        "id": 82472,
        "strassenbezeichnung": "Wupping"
    },
    {
        "kurzbezeichnung": "Neues Dorf",
        "id": 94074,
        "strassenbezeichnung": "Neues Dorf"
    },
    {
        "kurzbezeichnung": "Rennweg",
        "id": 96319,
        "strassenbezeichnung": "Rennweg"
    },
    {
        "kurzbezeichnung": "Gewerbegebiet",
        "id": 96320,
        "strassenbezeichnung": "Gewerbegebiet"
    },
    {
        "kurzbezeichnung": "Turmstraße",
        "id": 102220,
        "strassenbezeichnung": "Turmstraße"
    },
    {
        "kurzbezeichnung": "Königallee",
        "id": 112610,
        "strassenbezeichnung": "Königallee"
    },
    {
        "kurzbezeichnung": "St. Radegund",
        "id": 116212,
        "strassenbezeichnung": "St. Radegund"
    },
    {
        "kurzbezeichnung": "Acherstraße",
        "id": 116213,
        "strassenbezeichnung": "Acherstraße"
    },
    {
        "kurzbezeichnung": "Biri",
        "id": 116214,
        "strassenbezeichnung": "Biri"
    },
    {
        "kurzbezeichnung": "Ettenau",
        "id": 116215,
        "strassenbezeichnung": "Ettenau"
    },
    {
        "kurzbezeichnung": "Ahornweg",
        "id": 116216,
        "strassenbezeichnung": "Ahornweg"
    },
    {
        "kurzbezeichnung": "Sternenweg",
        "id": 116217,
        "strassenbezeichnung": "Sternenweg"
    },
    {
        "kurzbezeichnung": "Lärchenweg",
        "id": 116218,
        "strassenbezeichnung": "Lärchenweg"
    },
    {
        "kurzbezeichnung": "Birkenweg",
        "id": 116219,
        "strassenbezeichnung": "Birkenweg"
    },
    {
        "kurzbezeichnung": "Sonnenweg",
        "id": 116220,
        "strassenbezeichnung": "Sonnenweg"
    },
    {
        "kurzbezeichnung": "Erlenweg",
        "id": 116221,
        "strassenbezeichnung": "Erlenweg"
    },
    {
        "kurzbezeichnung": "Buchenweg",
        "id": 116222,
        "strassenbezeichnung": "Buchenweg"
    },
    {
        "kurzbezeichnung": "Sensberg",
        "id": 120124,
        "strassenbezeichnung": "Sensberg"
    },
    {
        "kurzbezeichnung": "Zimmerenglstraße",
        "id": 120350,
        "strassenbezeichnung": "Zimmerenglstraße"
    }
]