[
    {
        "kurzbezeichnung": "Adnet",
        "id": 87557,
        "strassenbezeichnung": "Adnet"
    },
    {
        "kurzbezeichnung": "Spumberg",
        "id": 87559,
        "strassenbezeichnung": "Spumberg"
    },
    {
        "kurzbezeichnung": "Waidach",
        "id": 87560,
        "strassenbezeichnung": "Waidach"
    },
    {
        "kurzbezeichnung": "Wimberg",
        "id": 87561,
        "strassenbezeichnung": "Wimberg"
    },
    {
        "kurzbezeichnung": "Gaißau",
        "id": 87573,
        "strassenbezeichnung": "Gaißau"
    },
    {
        "kurzbezeichnung": "Krispl",
        "id": 87574,
        "strassenbezeichnung": "Krispl"
    }
]