[
    {
        "kurzbezeichnung": "Kauns",
        "id": 89880,
        "strassenbezeichnung": "Kauns"
    },
    {
        "kurzbezeichnung": "Auchtweg",
        "id": 128147,
        "strassenbezeichnung": "Auchtweg"
    },
    {
        "kurzbezeichnung": "Bichl",
        "id": 128148,
        "strassenbezeichnung": "Bichl"
    },
    {
        "kurzbezeichnung": "Endgasse",
        "id": 128151,
        "strassenbezeichnung": "Endgasse"
    },
    {
        "kurzbezeichnung": "Kohlergasse",
        "id": 128161,
        "strassenbezeichnung": "Kohlergasse"
    },
    {
        "kurzbezeichnung": "Mösleweg",
        "id": 128165,
        "strassenbezeichnung": "Mösleweg"
    },
    {
        "kurzbezeichnung": "Plazerdellweg",
        "id": 128168,
        "strassenbezeichnung": "Plazerdellweg"
    },
    {
        "kurzbezeichnung": "Schulgasse",
        "id": 128169,
        "strassenbezeichnung": "Schulgasse"
    },
    {
        "kurzbezeichnung": "Sportplatzsiedlung",
        "id": 128171,
        "strassenbezeichnung": "Sportplatzsiedlung"
    },
    {
        "kurzbezeichnung": "Leitenweg",
        "id": 128174,
        "strassenbezeichnung": "Leitenweg"
    },
    {
        "kurzbezeichnung": "Ackerweg",
        "id": 128888,
        "strassenbezeichnung": "Ackerweg"
    }
]