[
    {
        "kurzbezeichnung": "Kapellenweg",
        "id": -30668,
        "strassenbezeichnung": "Kapellenweg"
    },
    {
        "kurzbezeichnung": "Schlossweg",
        "id": -30659,
        "strassenbezeichnung": "Schlossweg"
    },
    {
        "kurzbezeichnung": "Breitenfeld",
        "id": 88337,
        "strassenbezeichnung": "Breitenfeld"
    },
    {
        "kurzbezeichnung": "Tiefenbach",
        "id": 88376,
        "strassenbezeichnung": "Tiefenbach"
    },
    {
        "kurzbezeichnung": "Oberlamm",
        "id": 88506,
        "strassenbezeichnung": "Oberlamm"
    },
    {
        "kurzbezeichnung": "Stadtbergen",
        "id": 88516,
        "strassenbezeichnung": "Stadtbergen"
    },
    {
        "kurzbezeichnung": "Maierhofbergen",
        "id": 88531,
        "strassenbezeichnung": "Maierhofbergen"
    },
    {
        "kurzbezeichnung": "Aschbach",
        "id": 88557,
        "strassenbezeichnung": "Aschbach"
    },
    {
        "kurzbezeichnung": "Kohlgraben",
        "id": 88558,
        "strassenbezeichnung": "Kohlgraben"
    },
    {
        "kurzbezeichnung": "Ruppersdorf",
        "id": 88559,
        "strassenbezeichnung": "Ruppersdorf"
    },
    {
        "kurzbezeichnung": "Söchau",
        "id": 88560,
        "strassenbezeichnung": "Söchau"
    },
    {
        "kurzbezeichnung": "Tautendorf",
        "id": 88561,
        "strassenbezeichnung": "Tautendorf"
    },
    {
        "kurzbezeichnung": "Ebersdorf",
        "id": 88563,
        "strassenbezeichnung": "Ebersdorf"
    },
    {
        "kurzbezeichnung": "Hartl",
        "id": 88564,
        "strassenbezeichnung": "Hartl"
    },
    {
        "kurzbezeichnung": "Rittschein",
        "id": 88565,
        "strassenbezeichnung": "Rittschein"
    },
    {
        "kurzbezeichnung": "Übersbach",
        "id": 88566,
        "strassenbezeichnung": "Übersbach"
    },
    {
        "kurzbezeichnung": "Steinbergen",
        "id": 96851,
        "strassenbezeichnung": "Steinbergen"
    }
]