[
    {
        "kurzbezeichnung": "Aich",
        "id": 89156,
        "strassenbezeichnung": "Aich"
    },
    {
        "kurzbezeichnung": "Aigen",
        "id": 89157,
        "strassenbezeichnung": "Aigen"
    },
    {
        "kurzbezeichnung": "Aiglern",
        "id": 89158,
        "strassenbezeichnung": "Aiglern"
    },
    {
        "kurzbezeichnung": "Fischern",
        "id": 89159,
        "strassenbezeichnung": "Fischern"
    },
    {
        "kurzbezeichnung": "Gatschen",
        "id": 89160,
        "strassenbezeichnung": "Gatschen"
    },
    {
        "kurzbezeichnung": "Hohenberg",
        "id": 89161,
        "strassenbezeichnung": "Hohenberg"
    },
    {
        "kurzbezeichnung": "Ketten",
        "id": 89162,
        "strassenbezeichnung": "Ketten"
    },
    {
        "kurzbezeichnung": "Lantschern",
        "id": 89163,
        "strassenbezeichnung": "Lantschern"
    },
    {
        "kurzbezeichnung": "Mitteregg",
        "id": 89164,
        "strassenbezeichnung": "Mitteregg"
    },
    {
        "kurzbezeichnung": "Quilk",
        "id": 89165,
        "strassenbezeichnung": "Quilk"
    },
    {
        "kurzbezeichnung": "Ritzmannsdorf",
        "id": 89166,
        "strassenbezeichnung": "Ritzmannsdorf"
    },
    {
        "kurzbezeichnung": "Schlattham",
        "id": 89168,
        "strassenbezeichnung": "Schlattham"
    },
    {
        "kurzbezeichnung": "Tachenberg",
        "id": 89169,
        "strassenbezeichnung": "Tachenberg"
    },
    {
        "kurzbezeichnung": "Vorberg",
        "id": 89170,
        "strassenbezeichnung": "Vorberg"
    },
    {
        "kurzbezeichnung": "Sallaberg am Kulm",
        "id": 97589,
        "strassenbezeichnung": "Sallaberg am Kulm"
    },
    {
        "kurzbezeichnung": "Sallaberg am See",
        "id": 97590,
        "strassenbezeichnung": "Sallaberg am See"
    }
]